[
  {
    "id": 2,
    "name": "Old Pistol",
    "attackpattern": "Projectile",
    "value": 1,
    "dataId": "1|1|1|1|1|1|1|1|1|1|1|1|1|1|1|1|0|1|1|1|1|0|0|0|0|0",
    "attackbonus": 1,
    "speedbonus": 1,
    "healthbonus": 1,
    "criticalratebonus": 1,
    "criticaldmgbonus": 1,
    "attackspeedbonus": 1,
    "berserk": 1,
    "lifesteal": 1,
    "fireelement": 1,
    "iceelement": 1,
    "knockback": 1,
    "blazingtrail": 1,
    "stackdash": 1,
    "dashreflect": 1,
    "dashshockwave": 1,
    "conquestsmite": 1,
    "multishot": 0,
    "ricochet": 1,
    "piercing": 1,
    "lightningchain": 1,
    "projectileup": 1,
    "bouncing": 0,
    "deflect": 0,
    "rangeUp": 0,
    "dmgDashUp": 0,
    "rage": 0
  },
  {
    "id": 3,
    "name": "Rusty SMG",
    "attackpattern": "Projectile",
    "value": 1,
    "dataId": "1|1|1|1|1|1|1|1|1|1|1|1|1|1|1|1|0|1|1|1|1|0|0|0|0|0",
    "attackbonus": 1,
    "speedbonus": 1,
    "healthbonus": 1,
    "criticalratebonus": 1,
    "criticaldmgbonus": 1,
    "attackspeedbonus": 1,
    "berserk": 1,
    "lifesteal": 1,
    "fireelement": 1,
    "iceelement": 1,
    "knockback": 1,
    "blazingtrail": 1,
    "stackdash": 1,
    "dashreflect": 1,
    "dashshockwave": 1,
    "conquestsmite": 1,
    "multishot": 0,
    "ricochet": 1,
    "piercing": 1,
    "lightningchain": 1,
    "projectileup": 1,
    "bouncing": 0,
    "deflect": 0,
    "rangeUp": 0,
    "dmgDashUp": 0,
    "rage": 0
  },
  {
    "id": 4,
    "name": "Scrap Shotgun",
    "attackpattern": "Projectile",
    "value": 3,
    "dataId": "1|1|1|1|1|1|1|1|1|1|1|1|1|1|1|1|0|1|1|1|1|0|0|0|0|0",
    "attackbonus": 1,
    "speedbonus": 1,
    "healthbonus": 1,
    "criticalratebonus": 1,
    "criticaldmgbonus": 1,
    "attackspeedbonus": 1,
    "berserk": 1,
    "lifesteal": 1,
    "fireelement": 1,
    "iceelement": 1,
    "knockback": 1,
    "blazingtrail": 1,
    "stackdash": 1,
    "dashreflect": 1,
    "dashshockwave": 1,
    "conquestsmite": 1,
    "multishot": 0,
    "ricochet": 1,
    "piercing": 1,
    "lightningchain": 1,
    "projectileup": 1,
    "bouncing": 0,
    "deflect": 0,
    "rangeUp": 0,
    "dmgDashUp": 0,
    "rage": 0
  },
  {
    "id": 5,
    "name": "Dusty Rifle",
    "attackpattern": "Projectile",
    "value": 1,
    "dataId": "1|1|1|1|1|1|1|1|1|1|1|1|1|1|1|1|0|1|1|1|1|0|0|0|0|0",
    "attackbonus": 1,
    "speedbonus": 1,
    "healthbonus": 1,
    "criticalratebonus": 1,
    "criticaldmgbonus": 1,
    "attackspeedbonus": 1,
    "berserk": 1,
    "lifesteal": 1,
    "fireelement": 1,
    "iceelement": 1,
    "knockback": 1,
    "blazingtrail": 1,
    "stackdash": 1,
    "dashreflect": 1,
    "dashshockwave": 1,
    "conquestsmite": 1,
    "multishot": 0,
    "ricochet": 1,
    "piercing": 1,
    "lightningchain": 1,
    "projectileup": 1,
    "bouncing": 0,
    "deflect": 0,
    "rangeUp": 0,
    "dmgDashUp": 0,
    "rage": 0
  },
  {
    "id": 6,
    "name": "Blunt Machete",
    "attackpattern": "Slash",
    "value": 45,
    "dataId": "1|1|1|1|1|1|1|1|1|1|1|1|1|1|1|1|0|0|0|0|0|0|1|1|1|1",
    "attackbonus": 1,
    "speedbonus": 1,
    "healthbonus": 1,
    "criticalratebonus": 1,
    "criticaldmgbonus": 1,
    "attackspeedbonus": 1,
    "berserk": 1,
    "lifesteal": 1,
    "fireelement": 1,
    "iceelement": 1,
    "knockback": 1,
    "blazingtrail": 1,
    "stackdash": 1,
    "dashreflect": 1,
    "dashshockwave": 1,
    "conquestsmite": 1,
    "multishot": 0,
    "ricochet": 0,
    "piercing": 0,
    "lightningchain": 0,
    "projectileup": 0,
    "bouncing": 0,
    "deflect": 1,
    "rangeUp": 1,
    "dmgDashUp": 1,
    "rage": 1
  },
  {
    "id": 7,
    "name": "Classic Revolver",
    "attackpattern": "Projectile",
    "value": 1,
    "dataId": "1|1|1|1|1|1|1|1|1|1|1|1|1|1|1|1|0|1|1|1|1|0|0|0|0|0",
    "attackbonus": 1,
    "speedbonus": 1,
    "healthbonus": 1,
    "criticalratebonus": 1,
    "criticaldmgbonus": 1,
    "attackspeedbonus": 1,
    "berserk": 1,
    "lifesteal": 1,
    "fireelement": 1,
    "iceelement": 1,
    "knockback": 1,
    "blazingtrail": 1,
    "stackdash": 1,
    "dashreflect": 1,
    "dashshockwave": 1,
    "conquestsmite": 1,
    "multishot": 0,
    "ricochet": 1,
    "piercing": 1,
    "lightningchain": 1,
    "projectileup": 1,
    "bouncing": 0,
    "deflect": 0,
    "rangeUp": 0,
    "dmgDashUp": 0,
    "rage": 0
  },
  {
    "id": 8,
    "name": "Factory SMG",
    "attackpattern": "Projectile",
    "value": 1,
    "dataId": "1|1|1|1|1|1|1|1|1|1|1|1|1|1|1|1|0|1|1|1|1|0|0|0|0|0",
    "attackbonus": 1,
    "speedbonus": 1,
    "healthbonus": 1,
    "criticalratebonus": 1,
    "criticaldmgbonus": 1,
    "attackspeedbonus": 1,
    "berserk": 1,
    "lifesteal": 1,
    "fireelement": 1,
    "iceelement": 1,
    "knockback": 1,
    "blazingtrail": 1,
    "stackdash": 1,
    "dashreflect": 1,
    "dashshockwave": 1,
    "conquestsmite": 1,
    "multishot": 0,
    "ricochet": 1,
    "piercing": 1,
    "lightningchain": 1,
    "projectileup": 1,
    "bouncing": 0,
    "deflect": 0,
    "rangeUp": 0,
    "dmgDashUp": 0,
    "rage": 0
  },
  {
    "id": 9,
    "name": "Pump Action Shotgun",
    "attackpattern": "Projectile",
    "value": 3,
    "dataId": "1|1|1|1|1|1|1|1|1|1|1|1|1|1|1|1|0|1|1|1|1|0|0|0|0|0",
    "attackbonus": 1,
    "speedbonus": 1,
    "healthbonus": 1,
    "criticalratebonus": 1,
    "criticaldmgbonus": 1,
    "attackspeedbonus": 1,
    "berserk": 1,
    "lifesteal": 1,
    "fireelement": 1,
    "iceelement": 1,
    "knockback": 1,
    "blazingtrail": 1,
    "stackdash": 1,
    "dashreflect": 1,
    "dashshockwave": 1,
    "conquestsmite": 1,
    "multishot": 0,
    "ricochet": 1,
    "piercing": 1,
    "lightningchain": 1,
    "projectileup": 1,
    "bouncing": 0,
    "deflect": 0,
    "rangeUp": 0,
    "dmgDashUp": 0,
    "rage": 0
  },
  {
    "id": 10,
    "name": "Modern Assault Rifle",
    "attackpattern": "Projectile",
    "value": 1,
    "dataId": "1|1|1|1|1|1|1|1|1|1|1|1|1|1|1|1|0|1|1|1|1|0|0|0|0|0",
    "attackbonus": 1,
    "speedbonus": 1,
    "healthbonus": 1,
    "criticalratebonus": 1,
    "criticaldmgbonus": 1,
    "attackspeedbonus": 1,
    "berserk": 1,
    "lifesteal": 1,
    "fireelement": 1,
    "iceelement": 1,
    "knockback": 1,
    "blazingtrail": 1,
    "stackdash": 1,
    "dashreflect": 1,
    "dashshockwave": 1,
    "conquestsmite": 1,
    "multishot": 0,
    "ricochet": 1,
    "piercing": 1,
    "lightningchain": 1,
    "projectileup": 1,
    "bouncing": 0,
    "deflect": 0,
    "rangeUp": 0,
    "dmgDashUp": 0,
    "rage": 0
  },
  {
    "id": 11,
    "name": "Compound Bow",
    "attackpattern": "Projectile",
    "value": 1,
    "dataId": "1|1|1|1|1|1|1|1|1|1|1|1|1|1|1|1|0|0|0|1|1|0|0|0|0|0",
    "attackbonus": 1,
    "speedbonus": 1,
    "healthbonus": 1,
    "criticalratebonus": 1,
    "criticaldmgbonus": 1,
    "attackspeedbonus": 1,
    "berserk": 1,
    "lifesteal": 1,
    "fireelement": 1,
    "iceelement": 1,
    "knockback": 1,
    "blazingtrail": 1,
    "stackdash": 1,
    "dashreflect": 1,
    "dashshockwave": 1,
    "conquestsmite": 1,
    "multishot": 0,
    "ricochet": 0,
    "piercing": 0,
    "lightningchain": 1,
    "projectileup": 1,
    "bouncing": 0,
    "deflect": 0,
    "rangeUp": 0,
    "dmgDashUp": 0,
    "rage": 0
  },
  {
    "id": 12,
    "name": "Skull Hammer",
    "attackpattern": "Slam",
    "value": 1,
    "dataId": "1|1|1|1|1|1|1|1|1|1|1|1|1|1|1|1|0|0|0|0|0|0|0|1|1|1",
    "attackbonus": 1,
    "speedbonus": 1,
    "healthbonus": 1,
    "criticalratebonus": 1,
    "criticaldmgbonus": 1,
    "attackspeedbonus": 1,
    "berserk": 1,
    "lifesteal": 1,
    "fireelement": 1,
    "iceelement": 1,
    "knockback": 1,
    "blazingtrail": 1,
    "stackdash": 1,
    "dashreflect": 1,
    "dashshockwave": 1,
    "conquestsmite": 1,
    "multishot": 0,
    "ricochet": 0,
    "piercing": 0,
    "lightningchain": 0,
    "projectileup": 0,
    "bouncing": 0,
    "deflect": 0,
    "rangeUp": 1,
    "dmgDashUp": 1,
    "rage": 1
  },
  {
    "id": 13,
    "name": "Chainsword",
    "attackpattern": "Slash",
    "value": 45,
    "dataId": "1|1|1|1|1|1|1|1|1|1|1|1|1|1|1|1|0|0|0|0|0|0|1|1|1|1",
    "attackbonus": 1,
    "speedbonus": 1,
    "healthbonus": 1,
    "criticalratebonus": 1,
    "criticaldmgbonus": 1,
    "attackspeedbonus": 1,
    "berserk": 1,
    "lifesteal": 1,
    "fireelement": 1,
    "iceelement": 1,
    "knockback": 1,
    "blazingtrail": 1,
    "stackdash": 1,
    "dashreflect": 1,
    "dashshockwave": 1,
    "conquestsmite": 1,
    "multishot": 0,
    "ricochet": 0,
    "piercing": 0,
    "lightningchain": 0,
    "projectileup": 0,
    "bouncing": 0,
    "deflect": 1,
    "rangeUp": 1,
    "dmgDashUp": 1,
    "rage": 1
  },
  {
    "id": 14,
    "name": "Cinderstorm",
    "attackpattern": "Ray",
    "value": 1,
    "dataId": "1|1|1|1|1|1|1|1|1|1|1|1|1|1|1|1|0|0|0|1|1|0|0|0|0|0",
    "attackbonus": 1,
    "speedbonus": 1,
    "healthbonus": 1,
    "criticalratebonus": 1,
    "criticaldmgbonus": 1,
    "attackspeedbonus": 1,
    "berserk": 1,
    "lifesteal": 1,
    "fireelement": 1,
    "iceelement": 1,
    "knockback": 1,
    "blazingtrail": 1,
    "stackdash": 1,
    "dashreflect": 1,
    "dashshockwave": 1,
    "conquestsmite": 1,
    "multishot": 0,
    "ricochet": 0,
    "piercing": 0,
    "lightningchain": 1,
    "projectileup": 1,
    "bouncing": 0,
    "deflect": 0,
    "rangeUp": 0,
    "dmgDashUp": 0,
    "rage": 0
  },
  {
    "id": 15,
    "name": "Little Hunter",
    "attackpattern": "Projectile",
    "value": 1,
    "dataId": "1|1|1|1|1|1|1|1|1|1|1|1|1|1|1|1|0|1|1|1|1|0|0|0|0|0",
    "attackbonus": 1,
    "speedbonus": 1,
    "healthbonus": 1,
    "criticalratebonus": 1,
    "criticaldmgbonus": 1,
    "attackspeedbonus": 1,
    "berserk": 1,
    "lifesteal": 1,
    "fireelement": 1,
    "iceelement": 1,
    "knockback": 1,
    "blazingtrail": 1,
    "stackdash": 1,
    "dashreflect": 1,
    "dashshockwave": 1,
    "conquestsmite": 1,
    "multishot": 0,
    "ricochet": 1,
    "piercing": 1,
    "lightningchain": 1,
    "projectileup": 1,
    "bouncing": 0,
    "deflect": 0,
    "rangeUp": 0,
    "dmgDashUp": 0,
    "rage": 0
  },
  {
    "id": 16,
    "name": "Holemaker",
    "attackpattern": "Projectile",
    "value": 1,
    "dataId": "1|1|1|1|1|1|1|1|1|1|1|1|1|1|1|1|0|1|1|1|1|0|0|0|0|0",
    "attackbonus": 1,
    "speedbonus": 1,
    "healthbonus": 1,
    "criticalratebonus": 1,
    "criticaldmgbonus": 1,
    "attackspeedbonus": 1,
    "berserk": 1,
    "lifesteal": 1,
    "fireelement": 1,
    "iceelement": 1,
    "knockback": 1,
    "blazingtrail": 1,
    "stackdash": 1,
    "dashreflect": 1,
    "dashshockwave": 1,
    "conquestsmite": 1,
    "multishot": 0,
    "ricochet": 1,
    "piercing": 1,
    "lightningchain": 1,
    "projectileup": 1,
    "bouncing": 0,
    "deflect": 0,
    "rangeUp": 0,
    "dmgDashUp": 0,
    "rage": 0
  },
  {
    "id": 17,
    "name": "Luna",
    "attackpattern": "Slash",
    "value": 180,
    "dataId": "1|1|1|1|1|1|1|1|1|1|1|1|1|1|1|1|0|0|0|0|0|0|1|1|1|1",
    "attackbonus": 1,
    "speedbonus": 1,
    "healthbonus": 1,
    "criticalratebonus": 1,
    "criticaldmgbonus": 1,
    "attackspeedbonus": 1,
    "berserk": 1,
    "lifesteal": 1,
    "fireelement": 1,
    "iceelement": 1,
    "knockback": 1,
    "blazingtrail": 1,
    "stackdash": 1,
    "dashreflect": 1,
    "dashshockwave": 1,
    "conquestsmite": 1,
    "multishot": 0,
    "ricochet": 0,
    "piercing": 0,
    "lightningchain": 0,
    "projectileup": 0,
    "bouncing": 0,
    "deflect": 1,
    "rangeUp": 1,
    "dmgDashUp": 1,
    "rage": 1
  },
  {
    "id": 18,
    "name": "Crimson Arc",
    "attackpattern": "Slash",
    "value": 120,
    "dataId": "1|1|1|1|1|1|1|1|1|1|1|1|1|1|1|1|0|1|1|1|1|0|1|1|1|1",
    "attackbonus": 1,
    "speedbonus": 1,
    "healthbonus": 1,
    "criticalratebonus": 1,
    "criticaldmgbonus": 1,
    "attackspeedbonus": 1,
    "berserk": 1,
    "lifesteal": 1,
    "fireelement": 1,
    "iceelement": 1,
    "knockback": 1,
    "blazingtrail": 1,
    "stackdash": 1,
    "dashreflect": 1,
    "dashshockwave": 1,
    "conquestsmite": 1,
    "multishot": 0,
    "ricochet": 1,
    "piercing": 1,
    "lightningchain": 1,
    "projectileup": 1,
    "bouncing": 0,
    "deflect": 1,
    "rangeUp": 1,
    "dmgDashUp": 1,
    "rage": 1
  },
  {
    "id": 19,
    "name": "Heretic of Light",
    "attackpattern": "Slash",
    "value": 360,
    "dataId": "1|1|1|1|1|1|1|1|1|1|1|1|1|1|1|1|0|0|0|0|0|0|1|1|1|1",
    "attackbonus": 1,
    "speedbonus": 1,
    "healthbonus": 1,
    "criticalratebonus": 1,
    "criticaldmgbonus": 1,
    "attackspeedbonus": 1,
    "berserk": 1,
    "lifesteal": 1,
    "fireelement": 1,
    "iceelement": 1,
    "knockback": 1,
    "blazingtrail": 1,
    "stackdash": 1,
    "dashreflect": 1,
    "dashshockwave": 1,
    "conquestsmite": 1,
    "multishot": 0,
    "ricochet": 0,
    "piercing": 0,
    "lightningchain": 0,
    "projectileup": 0,
    "bouncing": 0,
    "deflect": 1,
    "rangeUp": 1,
    "dmgDashUp": 1,
    "rage": 1
  },
  {
    "id": 20,
    "name": "Sprayer Unlimited",
    "attackpattern": "Projectile",
    "value": 1,
    "dataId": "1|1|1|1|1|0|0|1|1|1|1|1|1|1|1|1|0|1|1|1|0|0|0|0|0|0",
    "attackbonus": 1,
    "speedbonus": 1,
    "healthbonus": 1,
    "criticalratebonus": 1,
    "criticaldmgbonus": 1,
    "attackspeedbonus": 0,
    "berserk": 0,
    "lifesteal": 1,
    "fireelement": 1,
    "iceelement": 1,
    "knockback": 1,
    "blazingtrail": 1,
    "stackdash": 1,
    "dashreflect": 1,
    "dashshockwave": 1,
    "conquestsmite": 1,
    "multishot": 0,
    "ricochet": 1,
    "piercing": 1,
    "lightningchain": 1,
    "projectileup": 0,
    "bouncing": 0,
    "deflect": 0,
    "rangeUp": 0,
    "dmgDashUp": 0,
    "rage": 0
  },
  {
    "id": 21,
    "name": "Dawnbreaker",
    "attackpattern": "Projectile",
    "value": 1,
    "dataId": "1|1|1|1|1|1|1|1|1|1|1|1|1|1|1|1|0|1|1|1|1|0|0|0|0|0",
    "attackbonus": 1,
    "speedbonus": 1,
    "healthbonus": 1,
    "criticalratebonus": 1,
    "criticaldmgbonus": 1,
    "attackspeedbonus": 1,
    "berserk": 1,
    "lifesteal": 1,
    "fireelement": 1,
    "iceelement": 1,
    "knockback": 1,
    "blazingtrail": 1,
    "stackdash": 1,
    "dashreflect": 1,
    "dashshockwave": 1,
    "conquestsmite": 1,
    "multishot": 0,
    "ricochet": 1,
    "piercing": 1,
    "lightningchain": 1,
    "projectileup": 1,
    "bouncing": 0,
    "deflect": 0,
    "rangeUp": 0,
    "dmgDashUp": 0,
    "rage": 0
  },
  {
    "id": 22,
    "name": "Angel’s Tears",
    "attackpattern": "AI",
    "value": 1,
    "dataId": "1|1|1|1|1|1|1|1|1|1|1|1|1|1|1|1|0|0|0|0|0|0|0|0|0|0",
    "attackbonus": 1,
    "speedbonus": 1,
    "healthbonus": 1,
    "criticalratebonus": 1,
    "criticaldmgbonus": 1,
    "attackspeedbonus": 1,
    "berserk": 1,
    "lifesteal": 1,
    "fireelement": 1,
    "iceelement": 1,
    "knockback": 1,
    "blazingtrail": 1,
    "stackdash": 1,
    "dashreflect": 1,
    "dashshockwave": 1,
    "conquestsmite": 1,
    "multishot": 0,
    "ricochet": 0,
    "piercing": 0,
    "lightningchain": 0,
    "projectileup": 0,
    "bouncing": 0,
    "deflect": 0,
    "rangeUp": 0,
    "dmgDashUp": 0,
    "rage": 0
  },
  {
    "id": 78,
    "name": "Long Rifle",
    "attackpattern": "Projectile",
    "value": 1,
    "dataId": "1|2|3|4|5|6|7|8|9|10|11|12|13|14|15|16|17|18|19|20|21|22|23|24|25|26",
    "attackbonus": 1,
    "speedbonus": 2,
    "healthbonus": 3,
    "criticalratebonus": 4,
    "criticaldmgbonus": 5,
    "attackspeedbonus": 6,
    "berserk": 7,
    "lifesteal": 8,
    "fireelement": 9,
    "iceelement": 10,
    "knockback": 11,
    "blazingtrail": 12,
    "stackdash": 13,
    "dashreflect": 14,
    "dashshockwave": 15,
    "conquestsmite": 16,
    "multishot": 17,
    "ricochet": 18,
    "piercing": 19,
    "lightningchain": 20,
    "projectileup": 21,
    "bouncing": 22,
    "deflect": 23,
    "rangeUp": 24,
    "dmgDashUp": 25,
    "rage": 26
  },
  {
    "id": 79,
    "name": "Dead Dance",
    "attackpattern": "Projectile",
    "value": 1,
    "dataId": "1|1|1|1|1|1|1|1|1|1|0|1|1|1|1|1|0|1|1|1|1|0|0|0|0|0",
    "attackbonus": 1,
    "speedbonus": 1,
    "healthbonus": 1,
    "criticalratebonus": 1,
    "criticaldmgbonus": 1,
    "attackspeedbonus": 1,
    "berserk": 1,
    "lifesteal": 1,
    "fireelement": 1,
    "iceelement": 1,
    "knockback": 0,
    "blazingtrail": 1,
    "stackdash": 1,
    "dashreflect": 1,
    "dashshockwave": 1,
    "conquestsmite": 1,
    "multishot": 0,
    "ricochet": 1,
    "piercing": 1,
    "lightningchain": 1,
    "projectileup": 1,
    "bouncing": 0,
    "deflect": 0,
    "rangeUp": 0,
    "dmgDashUp": 0,
    "rage": 0
  },
  {
    "id": 80,
    "name": "Explosion!!! ",
    "attackpattern": "Projectile",
    "value": 1,
    "dataId": "1|1|1|1|1|1|1|1|1|1|1|1|1|1|1|1|0|0|1|1|1|0|0|0|0|0",
    "attackbonus": 1,
    "speedbonus": 1,
    "healthbonus": 1,
    "criticalratebonus": 1,
    "criticaldmgbonus": 1,
    "attackspeedbonus": 1,
    "berserk": 1,
    "lifesteal": 1,
    "fireelement": 1,
    "iceelement": 1,
    "knockback": 1,
    "blazingtrail": 1,
    "stackdash": 1,
    "dashreflect": 1,
    "dashshockwave": 1,
    "conquestsmite": 1,
    "multishot": 0,
    "ricochet": 0,
    "piercing": 1,
    "lightningchain": 1,
    "projectileup": 1,
    "bouncing": 0,
    "deflect": 0,
    "rangeUp": 0,
    "dmgDashUp": 0,
    "rage": 0
  },
  {
    "id": 81,
    "name": "Flamethrower",
    "attackpattern": "Projectile",
    "value": 1,
    "dataId": "1|1|1|1|1|1|1|1|1|1|1|1|1|1|1|1|0|0|0|1|0|0|0|0|0|0",
    "attackbonus": 1,
    "speedbonus": 1,
    "healthbonus": 1,
    "criticalratebonus": 1,
    "criticaldmgbonus": 1,
    "attackspeedbonus": 1,
    "berserk": 1,
    "lifesteal": 1,
    "fireelement": 1,
    "iceelement": 1,
    "knockback": 1,
    "blazingtrail": 1,
    "stackdash": 1,
    "dashreflect": 1,
    "dashshockwave": 1,
    "conquestsmite": 1,
    "multishot": 0,
    "ricochet": 0,
    "piercing": 0,
    "lightningchain": 1,
    "projectileup": 0,
    "bouncing": 0,
    "deflect": 0,
    "rangeUp": 0,
    "dmgDashUp": 0,
    "rage": 0
  }
]
